[ {
		"id" : "1",
		"text" : "回收站",
		"href" : "opened.html",
		"icon" : "themes/windows/icons/bin.png",
		"cnf":{
			
		}
	}, {
		"id" : "2",
		"text" : "网络连接",
		"href" : "opened.html",
		"icon" : "themes/windows/icons/dns.png",
		"cnf":{
			
		}
	},{
		"id" : "3",
		"text" : "druid数据统计",
		"href" : "&{druid}",
		"icon" : "themes/windows/icons/computer.png",
		"cnf":{
			
		}
	},{
		"id" : "4",
		"text" : "考勤记录",
		"href" : "&{kaoqin}",
		"icon" : "themes/windows/icons/computer.png",
		"cnf":{
			
		}
	}
]

